{
  "posts": [
    {
      "id": "0",
      "author": "Darius",
      "title": "Post 1",
      "content": "Lorem ipsum dolor sit amet, consectetur adipisicing elit. Autem commodi cupiditate dolorem doloremque dolorum fugiat saepe sint soluta ullam voluptates voluptatum?",
      "img": "assets/photo-0.jpeg",
      "likes": 6
    },
    {
      "id": "1",
      "author": "Kazimieras",
      "title": "Post 2",
      "content": "Lorem ipsum dolor sit amet, consectetur adipisicing elit. Autem commodi cupiditate dolorem doloremque dolorum fugiat saepe sint soluta ullam voluptates voluptatum?",
      "img": "assets/photo-1.jpeg",
      "likes": 10
    },
    {
      "id": "2",
      "author": "Indrė",
      "title": "Post 3",
      "content": "Lorem ipsum dolor sit amet, consectetur adipisicing elit. Autem commodi cupiditate dolorem doloremque dolorum fugiat saepe sint soluta ullam voluptates voluptatum?",
      "img": "assets/photo-2.jpeg",
      "likes": 3
    },
    {
      "id": "3",
      "author": "Jurgis",
      "title": "Post 4",
      "likes": 2,
      "content": "Lorem ipsum dolor sit amet, consectetur adipisicing elit. Autem commodi cupiditate dolorem doloremque dolorum fugiat saepe sint soluta ullam voluptates voluptatum?"
    },
    {
      "id": "4",
      "author": "Laura",
      "title": "Post 5",
      "content": "Lorem ipsum dolor sit amet, consectetur adipisicing elit. Autem commodi cupiditate dolorem doloremque dolorum fugiat saepe sint soluta ullam voluptates voluptatum?",
      "img": "assets/photo-4.jpeg",
      "likes": 5
    },
    {
      "id": "5",
      "author": "Minijus",
      "title": "Post 6",
      "content": "Lorem ipsum dolor sit amet, consectetur adipisicing elit. Autem commodi cupiditate dolorem doloremque dolorum fugiat saepe sint soluta ullam voluptates voluptatum?",
      "img": "assets/photo-5.jpeg",
      "likes": 0
    },
    {
      "author": "Gabrielius",
      "title": "Bandymas",
      "content": "!important",
      "id": "6",
      "likes": 1
    },
    {
      "author": "Armandas",
      "title": "This is Something",
      "content": "OK",
      "id": "7",
      "likes": 0
    },
    {
      "author": "adsa",
      "title": "asdas",
      "content": "asdas",
      "id": "JrDA0Yp",
      "likes": 0
    },
    {
      "author": "dsadasdas",
      "title": "asdasdas",
      "content": "asdasda",
      "id": "2CKS52Y",
      "likes": 0
    },
    {
      "author": "Gabrielius",
      "title": "This is Something",
      "content": "Boo!",
      "id": "tvmnyN3",
      "likes": 0
    },
    {
      "author": "Gabrielius",
      "title": "Heuristics",
      "content": "OKAI",
      "id": "iq-IUtM",
      "likes": 0
    },
    {
      "author": null,
      "title": null,
      "content": null,
      "id": "9W5LSzL",
      "likes": 0
    },
    {
      "author": "Gabrielius",
      "title": "Another One",
      "content": "asa",
      "id": "K3aPsSJ",
      "likes": 0
    },
    {
      "author": null,
      "title": null,
      "content": null,
      "id": "pTvcq5v",
      "likes": 0
    },
    {
      "author": null,
      "title": null,
      "content": null,
      "id": "ojI5bbY",
      "likes": 0
    },
    {
      "author": "asdas",
      "title": "asdas",
      "content": "asdasd",
      "id": "WMSrjG5",
      "likes": 0
    },
    {
      "author": "asdasdas",
      "title": "asdasdsad",
      "content": "asdsadsadas",
      "id": "gWAZOG0",
      "likes": 0
    },
    {
      "author": "next",
      "title": "next",
      "content": "next",
      "likes": 0,
      "id": "yRGjMaX"
    }
  ]
}